source/Conqace/__init__.py
source/Conqace/__main__.py
conqace-0.2.0.dist-info/LICENSE
conqace-0.2.0.dist-info/METADATA
conqace-0.2.0.dist-info/WHEEL
conqace-0.2.0.dist-info/RECORD
