Metadata-Version: 2.1
Name: Conqace
Version: 0.2.0
Summary: A Python-based update manager.
Author: Your Name
Author-email: you@example.com
Requires-Python: >=3.10
Classifier: Programming Language :: Python :: 3
Classifier: Programming Language :: Python :: 3.10
Classifier: Programming Language :: Python :: 3.11
Classifier: Programming Language :: Python :: 3.12
Requires-Dist: cryptography (>=42.0.8,<43.0.0)
Requires-Dist: distro (>=1.9.0,<2.0.0)
Requires-Dist: keyring (>=25.2.1,<26.0.0)
Requires-Dist: loguru (>=0.7.2,<0.8.0)
Requires-Dist: nox (>=2024.4.15,<2025.0.0)
Requires-Dist: pip-tools (>=7.4.1,<8.0.0)
Requires-Dist: python-dotenv (>=1.0.1,<2.0.0)
Requires-Dist: requests (>=2.32.3,<3.0.0)
Requires-Dist: sphinx (>=7.3.7,<8.0.0)
